{
  "artifacts": {
    "cities_data.json": {
      "generated_at": "2026-07-21T00:27:12+00:00",
      "sha256": "ab41bb38de8a0a6bd3f1379ebd23d32fba278e10d7c1584cb5de6f014fd630c4",
      "status": "ready"
    },
    "forecast_data.json": {
      "generated_at": "2026-07-09T21:48:53+00:00",
      "sha256": "b6ee97371a24bf467ad3543a710b588868a65cba6cc80878e7781d31e2ff060d",
      "status": "ready"
    },
    "strategy_research.json": {
      "generated_at": "2026-07-21T00:21:57+00:00",
      "sha256": "cf527ebc2ea023d182d235d122692658704e4718450954ebde82614c17c2a231",
      "status": "preserved"
    },
    "trading_signal.json": {
      "generated_at": "2026-07-21T00:27:08+00:00",
      "sha256": "0df5d1282cb9a979921aadab6a1d2d53d5feb9c968279e947fdef11dbb6dd775",
      "status": "ready"
    },
    "weather_story_data.json": {
      "generated_at": "2026-07-09T21:48:53+00:00",
      "sha256": "f5587b28e6b6c6b63ff69eaf91afcb063d91dab5eac2001db363715f63af9048",
      "status": "ready"
    }
  },
  "provenance": {
    "accounting_policy_version": "acct-v4-account-scoped-2026-07-14",
    "execution_model_version": "exec-v4-2026-07-17",
    "source_dirty": false,
    "source_sha": "6591946155ecfe9f690109d90b137f1b667dfdd9",
    "synced_at_utc": "2026-07-20T06:38:18Z"
  },
  "published_at": "2026-07-21T00:27:12+00:00",
  "schema_version": 1,
  "snapshot_id": "38acc1051c16166f79e82dca"
}
