{
  "artifacts": {
    "cities_data.json": {
      "generated_at": "2026-07-23T00:25:06+00:00",
      "sha256": "fdcff579d94630d475d5076c7243d0c48a7dbcea56dc6ad2872495faf1454b9d",
      "status": "ready"
    },
    "forecast_data.json": {
      "generated_at": "2026-07-09T21:48:53+00:00",
      "sha256": "b6ee97371a24bf467ad3543a710b588868a65cba6cc80878e7781d31e2ff060d",
      "status": "ready"
    },
    "strategy_research.json": {
      "generated_at": "2026-07-23T00:25:01+00:00",
      "sha256": "976adae87a5394076d18a7e635450811b1909b042018f53818879cacd1e726e1",
      "status": "preserved"
    },
    "trading_signal.json": {
      "generated_at": "2026-07-23T00:25:01+00:00",
      "sha256": "ba5e9f10da8cbffd87eedacd9a6e962a22b755b96fb10006dbbba857f966625a",
      "status": "ready"
    },
    "weather_story_data.json": {
      "generated_at": "2026-07-09T21:48:53+00:00",
      "sha256": "f5587b28e6b6c6b63ff69eaf91afcb063d91dab5eac2001db363715f63af9048",
      "status": "ready"
    }
  },
  "provenance": {
    "accounting_policy_version": "acct-v4-account-scoped-2026-07-14",
    "execution_model_version": "exec-v4-2026-07-17",
    "source_dirty": false,
    "source_sha": "ac21ec486012a92ef351f0f4742bc4b9a4dc42a2",
    "synced_at_utc": "2026-07-22T09:45:16Z"
  },
  "published_at": "2026-07-23T00:25:06+00:00",
  "schema_version": 1,
  "snapshot_id": "d865c3a7f24a3915f5d15b6e"
}
