{
  "artifacts": {
    "cities_data.json": {
      "generated_at": "2026-07-23T19:52:49+00:00",
      "sha256": "fe7e04c7d42bb46f6f6b09b4c25be372c02ecdc4e08a7a7155ff827a510e6b65",
      "status": "ready"
    },
    "forecast_data.json": {
      "generated_at": "2026-07-09T21:48:53+00:00",
      "sha256": "b6ee97371a24bf467ad3543a710b588868a65cba6cc80878e7781d31e2ff060d",
      "status": "ready"
    },
    "strategy_research.json": {
      "generated_at": "2026-07-23T19:45:57+00:00",
      "sha256": "86fe845d7f0dbda8163123185da9341c1556a13b0f62d149ad636178ec4c7df6",
      "status": "preserved"
    },
    "trading_signal.json": {
      "generated_at": "2026-07-23T19:52:45+00:00",
      "sha256": "38fd7f2938d37d93f6c33e9adbf472458c4e7ba6072d2e7f7a74afecccaa0e4b",
      "status": "ready"
    },
    "weather_story_data.json": {
      "generated_at": "2026-07-09T21:48:53+00:00",
      "sha256": "f5587b28e6b6c6b63ff69eaf91afcb063d91dab5eac2001db363715f63af9048",
      "status": "ready"
    }
  },
  "provenance": {
    "accounting_policy_version": "acct-v4-account-scoped-2026-07-14",
    "execution_model_version": "exec-v4-2026-07-17",
    "source_dirty": false,
    "source_sha": "ac21ec486012a92ef351f0f4742bc4b9a4dc42a2",
    "synced_at_utc": "2026-07-22T09:45:16Z"
  },
  "published_at": "2026-07-23T19:52:50+00:00",
  "schema_version": 1,
  "snapshot_id": "ca7a85e99c13f6bfd38ab43e"
}
