{
  "artifacts": {
    "cities_data.json": {
      "generated_at": "2026-07-13T01:44:46+00:00",
      "sha256": "050392274b663101e91cb94724bd0edec5b9d17a456eb46cdc9a7f82459b49ee",
      "status": "ready"
    },
    "forecast_data.json": {
      "generated_at": "2026-07-09T21:48:53+00:00",
      "sha256": "b6ee97371a24bf467ad3543a710b588868a65cba6cc80878e7781d31e2ff060d",
      "status": "ready"
    },
    "strategy_research.json": {
      "generated_at": "2026-07-13T01:37:53+00:00",
      "sha256": "0ca1ef7183be440a73e085b88afc7cd4caa8b55fb1a78196f783a2287c70185f",
      "status": "preserved"
    },
    "trading_signal.json": {
      "generated_at": "2026-07-13T01:44:42+00:00",
      "sha256": "e2b20900f6d2b1cb2fb90d5eecdb76cf05fc53234fa8f631de561d6341e58c1b",
      "status": "ready"
    },
    "weather_story_data.json": {
      "generated_at": "2026-07-09T21:48:53+00:00",
      "sha256": "f5587b28e6b6c6b63ff69eaf91afcb063d91dab5eac2001db363715f63af9048",
      "status": "ready"
    }
  },
  "published_at": "2026-07-13T01:44:46+00:00",
  "schema_version": 1,
  "snapshot_id": "410b7ff85c4d511b417d1ddc"
}
