{
  "artifacts": {
    "cities_data.json": {
      "generated_at": "2026-07-17T02:28:46+00:00",
      "sha256": "4c3a90b61276fea25a26eccdb8599dbd796f26df596de594e170b40ceb3e3005",
      "status": "ready"
    },
    "forecast_data.json": {
      "generated_at": "2026-07-09T21:48:53+00:00",
      "sha256": "b6ee97371a24bf467ad3543a710b588868a65cba6cc80878e7781d31e2ff060d",
      "status": "ready"
    },
    "strategy_research.json": {
      "generated_at": "2026-07-17T02:21:13+00:00",
      "sha256": "6d74f711ab68630052bcaca9d96137e19755b0484c04ba29912043942830ecc7",
      "status": "preserved"
    },
    "trading_signal.json": {
      "generated_at": "2026-07-17T02:28:42+00:00",
      "sha256": "cd50493786a45c3b3cb205efeed835ee4f2dcf84d308beb982dfaf8a69f0fb4a",
      "status": "ready"
    },
    "weather_story_data.json": {
      "generated_at": "2026-07-09T21:48:53+00:00",
      "sha256": "f5587b28e6b6c6b63ff69eaf91afcb063d91dab5eac2001db363715f63af9048",
      "status": "ready"
    }
  },
  "provenance": {
    "accounting_policy_version": "acct-v4-account-scoped-2026-07-14",
    "execution_model_version": "exec-v3-2026-07-14",
    "source_dirty": false,
    "source_sha": "803bfad5f77b3a703d31a52471b5f1b4389dafeb",
    "synced_at_utc": "2026-07-15T00:31:42Z"
  },
  "published_at": "2026-07-17T02:28:46+00:00",
  "schema_version": 1,
  "snapshot_id": "23179a9b6cfb7d61af132765"
}
