{
  "artifacts": {
    "cities_data.json": {
      "generated_at": "2026-07-24T05:18:32+00:00",
      "sha256": "feaa1ba16310c355fb1ff322f671df54417d48151143d6334418597484692938",
      "status": "ready"
    },
    "forecast_data.json": {
      "generated_at": "2026-07-09T21:48:53+00:00",
      "sha256": "b6ee97371a24bf467ad3543a710b588868a65cba6cc80878e7781d31e2ff060d",
      "status": "ready"
    },
    "strategy_research.json": {
      "generated_at": "2026-07-24T05:17:24+00:00",
      "sha256": "a0d2f846cae672e81e3895aa19a1b1bfc0f2190a70d00d0df95873d89d401dac",
      "status": "preserved"
    },
    "trading_signal.json": {
      "generated_at": "2026-07-24T05:18:28+00:00",
      "sha256": "ff8f3ed43b33de56cdd90d365101725c4d7872a1347f36563ccaf841ec555082",
      "status": "ready"
    },
    "weather_story_data.json": {
      "generated_at": "2026-07-09T21:48:53+00:00",
      "sha256": "f5587b28e6b6c6b63ff69eaf91afcb063d91dab5eac2001db363715f63af9048",
      "status": "ready"
    }
  },
  "provenance": {
    "accounting_policy_version": "acct-v4-account-scoped-2026-07-14",
    "execution_model_version": "exec-v4-2026-07-17",
    "source_dirty": false,
    "source_sha": "ac21ec486012a92ef351f0f4742bc4b9a4dc42a2",
    "synced_at_utc": "2026-07-22T09:45:16Z"
  },
  "published_at": "2026-07-24T05:18:32+00:00",
  "schema_version": 1,
  "snapshot_id": "62baf0f8b6d1c7eff350b700"
}
