{
  "artifacts": {
    "cities_data.json": {
      "generated_at": "2026-07-12T00:05:08+00:00",
      "sha256": "3b61b35fad7c69a863b47ebff55e6e20128ff510c96642cdcf7dcf5219ca443f",
      "status": "ready"
    },
    "forecast_data.json": {
      "generated_at": "2026-07-09T21:48:53+00:00",
      "sha256": "b6ee97371a24bf467ad3543a710b588868a65cba6cc80878e7781d31e2ff060d",
      "status": "ready"
    },
    "strategy_research.json": {
      "generated_at": "2026-07-11T23:55:56+00:00",
      "sha256": "fdf763fb4bd59527c7d9e8015fe9721baff7fa531c4905a599fcda4e9f01d1ac",
      "status": "preserved"
    },
    "trading_signal.json": {
      "generated_at": "2026-07-12T00:05:06+00:00",
      "sha256": "d2138adaaf2a7171da92788f8bddd4e53d38caddeff308a5070adad59ca545c5",
      "status": "ready"
    },
    "weather_story_data.json": {
      "generated_at": "2026-07-09T21:48:53+00:00",
      "sha256": "f5587b28e6b6c6b63ff69eaf91afcb063d91dab5eac2001db363715f63af9048",
      "status": "ready"
    }
  },
  "published_at": "2026-07-12T00:05:09+00:00",
  "schema_version": 1,
  "snapshot_id": "b1be35052151562556d53311"
}
