{
  "artifacts": {
    "cities_data.json": {
      "generated_at": "2026-07-13T14:26:06+00:00",
      "sha256": "a309022b7dd04a9d09647976af96309a78943f214729227cb783fd9b52cae3a6",
      "status": "ready"
    },
    "forecast_data.json": {
      "generated_at": "2026-07-09T21:48:53+00:00",
      "sha256": "b6ee97371a24bf467ad3543a710b588868a65cba6cc80878e7781d31e2ff060d",
      "status": "ready"
    },
    "strategy_research.json": {
      "generated_at": "2026-07-13T14:31:08+00:00",
      "sha256": "e5986343165ccb3fbc83ab4680ce7f1374ff920f0659152c6d13efafb213fee3",
      "status": "ready"
    },
    "trading_signal.json": {
      "generated_at": "2026-07-13T14:26:02+00:00",
      "sha256": "5cedd1d1d5b5d941c9a1ac6eafa3a670383f2ff6cb47d344b30d8787705dcdf4",
      "status": "ready"
    },
    "weather_story_data.json": {
      "generated_at": "2026-07-09T21:48:53+00:00",
      "sha256": "f5587b28e6b6c6b63ff69eaf91afcb063d91dab5eac2001db363715f63af9048",
      "status": "ready"
    }
  },
  "published_at": "2026-07-13T14:31:08+00:00",
  "schema_version": 1,
  "snapshot_id": "0fde381291bf41ac74d6d07d"
}
