{
  "calibration": {
    "avg_entropy": 1.077,
    "avg_winning_probability": 0.4815,
    "brier_score": 0.5314,
    "buckets": [
      {
        "avg_probability": 0.0304,
        "brier_score": 0.0344,
        "calibration_gap": 0.0066,
        "count": 810,
        "lower": 0.0,
        "observed_frequency": 0.037,
        "range": "0.0-0.1",
        "upper": 0.1
      },
      {
        "avg_probability": 0.1518,
        "brier_score": 0.1211,
        "calibration_gap": -0.009,
        "count": 371,
        "lower": 0.1,
        "observed_frequency": 0.1429,
        "range": "0.1-0.2",
        "upper": 0.2
      },
      {
        "avg_probability": 0.2274,
        "brier_score": 0.1956,
        "calibration_gap": 0.0377,
        "count": 215,
        "lower": 0.2,
        "observed_frequency": 0.2651,
        "range": "0.2-0.3",
        "upper": 0.3
      },
      {
        "avg_probability": 0.3525,
        "brier_score": 0.1593,
        "calibration_gap": -0.2096,
        "count": 14,
        "lower": 0.3,
        "observed_frequency": 0.1429,
        "range": "0.3-0.4",
        "upper": 0.4
      },
      {
        "avg_probability": 0.4591,
        "brier_score": 0.2321,
        "calibration_gap": -0.1113,
        "count": 23,
        "lower": 0.4,
        "observed_frequency": 0.3478,
        "range": "0.4-0.5",
        "upper": 0.5
      },
      {
        "avg_probability": 0.5444,
        "brier_score": 0.2537,
        "calibration_gap": -0.1,
        "count": 18,
        "lower": 0.5,
        "observed_frequency": 0.4444,
        "range": "0.5-0.6",
        "upper": 0.6
      },
      {
        "avg_probability": 0.6475,
        "brier_score": 0.2562,
        "calibration_gap": -0.1475,
        "count": 14,
        "lower": 0.6,
        "observed_frequency": 0.5,
        "range": "0.6-0.7",
        "upper": 0.7
      },
      {
        "avg_probability": 0.7481,
        "brier_score": 0.1972,
        "calibration_gap": -0.0338,
        "count": 14,
        "lower": 0.7,
        "observed_frequency": 0.7143,
        "range": "0.7-0.8",
        "upper": 0.8
      },
      {
        "avg_probability": 0.8541,
        "brier_score": 0.057,
        "calibration_gap": 0.1024,
        "count": 23,
        "lower": 0.8,
        "observed_frequency": 0.9565,
        "range": "0.8-0.9",
        "upper": 0.9
      },
      {
        "avg_probability": 0.967,
        "brier_score": 0.0654,
        "calibration_gap": -0.0384,
        "count": 70,
        "lower": 0.9,
        "observed_frequency": 0.9286,
        "range": "0.9-1.0",
        "upper": 1.0
      }
    ],
    "cohorts": [
      {
        "avg_winning_probability": 0.9405,
        "brier_score": 0.0155,
        "count": 50,
        "log_loss": 0.0677,
        "name": "cold_below_60f",
        "top_bin_accuracy": 1.0
      },
      {
        "avg_winning_probability": 0.478,
        "brier_score": 0.5258,
        "count": 139,
        "log_loss": 1.0789,
        "name": "normal_60_69f",
        "top_bin_accuracy": 0.6331
      },
      {
        "avg_winning_probability": 0.1725,
        "brier_score": 0.9039,
        "count": 65,
        "log_loss": 1.9731,
        "name": "warm_70_79f",
        "top_bin_accuracy": 0.1231
      },
      {
        "avg_winning_probability": 0.1828,
        "brier_score": 0.8263,
        "count": 8,
        "log_loss": 1.7862,
        "name": "hot_80f_plus",
        "top_bin_accuracy": 0.125
      }
    ],
    "log_loss": 1.1293,
    "n": 262,
    "source": "lstm",
    "top_bin_accuracy": 0.5611,
    "warnings": [
      "Mid-probability buckets are overconfident: 0.5-0.6 averages 0.544 but resolves 0.444."
    ]
  },
  "disclaimer": "Paper-trading research only. This report does not place live orders.",
  "live_orders_enabled": false,
  "mode": "paper_research_only",
  "schema_version": 1,
  "summary": {
    "approved_signal_count": 0,
    "best_signal": {
      "action": "BUY_YES",
      "approved": false,
      "ask": 0.0,
      "bid": 0.0,
      "decision": "NO_TRADE",
      "edge": 0.341,
      "edge_lcb": 0.135,
      "ensemble_probability": 0.6774,
      "expected_profit": 0.0,
      "intraday_probability": null,
      "label": "66\u00b0 to 67\u00b0",
      "market_available": true,
      "market_probability": null,
      "model_probability": 0.341,
      "probability": 0.341,
      "probability_lcb": 0.135,
      "reasons": [
        "market status is initialized, not active",
        "YES ask is not tradeable"
      ],
      "recommended_contracts": 0.0,
      "recommended_spend": 0.0,
      "remaining_heat_risk": null,
      "residual_probability": 0.1969,
      "side": "YES",
      "spread": 0.0,
      "target_date": "2026-06-26",
      "ticker": "KXHIGHTSFO-26JUN26-B66.5",
      "trade_quality_score": 64.2
    },
    "target_count": 2
  },
  "targets": [
    {
      "best_decision": {
        "action": "BUY_NO",
        "approved": false,
        "ask": 0.65,
        "bid": 0.64,
        "decision": "NO_TRADE",
        "edge": 0.0626,
        "edge_lcb": -0.1697,
        "ensemble_probability": 1.0,
        "expected_profit": 0.0,
        "intraday_probability": 0.878,
        "label": "71\u00b0 or above",
        "market_probability": 0.6553,
        "model_probability": 0.8761,
        "probability": 0.7326,
        "probability_lcb": 0.5003,
        "reasons": [
          "forecast source spread 8.1F exceeds max 7.0F; point blend is unreliable",
          "model/market gap 0.221 exceeds max 0.150",
          "lower-bound edge -0.170 below min 0.000"
        ],
        "recommended_contracts": 0.0,
        "recommended_spend": 0.0,
        "remaining_heat_risk": 0.904,
        "residual_probability": 0.8222,
        "side": "NO",
        "spread": 0.01,
        "ticker": "KXHIGHTSFO-26JUN25-T70",
        "trade_quality_score": 45.8
      },
      "decisions": [
        {
          "action": "BUY_NO",
          "approved": false,
          "ask": 0.65,
          "bid": 0.64,
          "decision": "NO_TRADE",
          "edge": 0.0626,
          "edge_lcb": -0.1697,
          "ensemble_probability": 1.0,
          "expected_profit": 0.0,
          "intraday_probability": 0.878,
          "label": "71\u00b0 or above",
          "market_probability": 0.6553,
          "model_probability": 0.8761,
          "probability": 0.7326,
          "probability_lcb": 0.5003,
          "reasons": [
            "forecast source spread 8.1F exceeds max 7.0F; point blend is unreliable",
            "model/market gap 0.221 exceeds max 0.150",
            "lower-bound edge -0.170 below min 0.000"
          ],
          "recommended_contracts": 0.0,
          "recommended_spend": 0.0,
          "remaining_heat_risk": 0.904,
          "residual_probability": 0.8222,
          "side": "NO",
          "spread": 0.01,
          "ticker": "KXHIGHTSFO-26JUN25-T70",
          "trade_quality_score": 45.8
        },
        {
          "action": "BUY_NO",
          "approved": false,
          "ask": 1.0,
          "bid": 0.99,
          "decision": "NO_TRADE",
          "edge": -0.0375,
          "edge_lcb": -0.075,
          "ensemble_probability": 1.0,
          "expected_profit": -0.0,
          "intraday_probability": 0.904,
          "label": "62\u00b0 or below",
          "market_probability": 0.9951,
          "model_probability": 0.9019,
          "probability": 0.9625,
          "probability_lcb": 0.925,
          "reasons": [
            "forecast source spread 8.1F exceeds max 7.0F; point blend is unreliable",
            "NO ask is not tradeable",
            "all-in cost 1.00 meets or exceeds the $1 contract payout",
            "edge -0.038 below min 0.020",
            "lower-bound edge -0.075 below min 0.000"
          ],
          "recommended_contracts": 0.0,
          "recommended_spend": 0.0,
          "remaining_heat_risk": 0.904,
          "residual_probability": 0.8588,
          "side": "NO",
          "spread": 0.01,
          "ticker": "KXHIGHTSFO-26JUN25-T63",
          "trade_quality_score": 44.4
        },
        {
          "action": "BUY_NO",
          "approved": false,
          "ask": 0.95,
          "bid": 0.94,
          "decision": "NO_TRADE",
          "edge": -0.0783,
          "edge_lcb": -0.1965,
          "ensemble_probability": 0.6774,
          "expected_profit": -0.0,
          "intraday_probability": 0.7736,
          "label": "65\u00b0 to 66\u00b0",
          "market_probability": 0.9466,
          "model_probability": 0.7613,
          "probability": 0.8817,
          "probability_lcb": 0.7635,
          "reasons": [
            "forecast source spread 8.1F exceeds max 7.0F; point blend is unreliable",
            "model/market gap 0.185 exceeds max 0.150",
            "edge -0.078 below min 0.020",
            "lower-bound edge -0.197 below min 0.000"
          ],
          "recommended_contracts": 0.0,
          "recommended_spend": 0.0,
          "remaining_heat_risk": 0.904,
          "residual_probability": 0.7913,
          "side": "NO",
          "spread": 0.01,
          "ticker": "KXHIGHTSFO-26JUN25-B65.5",
          "trade_quality_score": 41.4
        },
        {
          "action": "BUY_YES",
          "approved": false,
          "ask": 0.37,
          "bid": 0.36,
          "decision": "NO_TRADE",
          "edge": -0.1218,
          "edge_lcb": -0.3526,
          "ensemble_probability": 0.0,
          "expected_profit": -0.0,
          "intraday_probability": 0.1694,
          "label": "69\u00b0 to 70\u00b0",
          "market_probability": 0.3544,
          "model_probability": 0.1081,
          "probability": 0.2682,
          "probability_lcb": 0.0374,
          "reasons": [
            "forecast source spread 8.1F exceeds max 7.0F; point blend is unreliable",
            "YES ask size 0.70 below min 1.00; no displayed entry liquidity",
            "model/market gap 0.246 exceeds max 0.150",
            "edge -0.122 below min 0.020",
            "lower-bound edge -0.353 below min 0.000",
            "YES lower-bound edge -0.353 is not positive"
          ],
          "recommended_contracts": 0.0,
          "recommended_spend": 0.0,
          "remaining_heat_risk": 0.904,
          "residual_probability": 0.1253,
          "side": "YES",
          "spread": 0.01,
          "ticker": "KXHIGHTSFO-26JUN25-B69.5",
          "trade_quality_score": 41.1
        },
        {
          "action": "BUY_NO",
          "approved": false,
          "ask": 0.8,
          "bid": 0.75,
          "decision": "NO_TRADE",
          "edge": -0.0847,
          "edge_lcb": -0.334,
          "ensemble_probability": 0.3226,
          "expected_profit": -0.0,
          "intraday_probability": 0.7647,
          "label": "67\u00b0 to 68\u00b0",
          "market_probability": 0.7816,
          "model_probability": 0.6963,
          "probability": 0.7353,
          "probability_lcb": 0.486,
          "reasons": [
            "forecast source spread 8.1F exceeds max 7.0F; point blend is unreliable",
            "edge -0.085 below min 0.020",
            "lower-bound edge -0.334 below min 0.000"
          ],
          "recommended_contracts": 0.0,
          "recommended_spend": 0.0,
          "remaining_heat_risk": 0.904,
          "residual_probability": 0.8239,
          "side": "NO",
          "spread": 0.05,
          "ticker": "KXHIGHTSFO-26JUN25-B67.5",
          "trade_quality_score": 36.2
        },
        {
          "action": "BUY_YES",
          "approved": false,
          "ask": 0.03,
          "bid": 0.02,
          "decision": "NO_TRADE",
          "edge": 0.0204,
          "edge_lcb": -0.04,
          "ensemble_probability": 0.0,
          "expected_profit": 0.0,
          "intraday_probability": 0.1509,
          "label": "63\u00b0 to 64\u00b0",
          "market_probability": 0.0243,
          "model_probability": 0.1275,
          "probability": 0.0604,
          "probability_lcb": 0.0,
          "reasons": [
            "forecast source spread 8.1F exceeds max 7.0F; point blend is unreliable",
            "posterior probability 0.060 below min 0.070",
            "lower-bound edge -0.040 below min 0.000",
            "1c/2c tail requires exceptional support (YES): p_lcb 0.000<0.090, edge_lcb -0.040<0.030, model/market gap 0.103>0.080, ensemble p 0.000<0.080",
            "YES lower-bound edge -0.040 is not positive",
            "cheap YES (cost 0.04) needs point probability >= 2x cost (0.08); have 0.06"
          ],
          "recommended_contracts": 0.0,
          "recommended_spend": 0.0,
          "remaining_heat_risk": 0.904,
          "residual_probability": 0.171,
          "side": "YES",
          "spread": 0.01,
          "ticker": "KXHIGHTSFO-26JUN25-B63.5",
          "trade_quality_score": 35.0
        },
        {
          "action": "BUY_NO",
          "approved": false,
          "ask": 0.64,
          "bid": 0.63,
          "decision": "NO_TRADE",
          "edge": 0.0718,
          "edge_lcb": -0.159,
          "ensemble_probability": 1.0,
          "expected_profit": 0.0,
          "intraday_probability": 0.8306,
          "label": "69\u00b0 to 70\u00b0",
          "market_probability": 0.6456,
          "model_probability": 0.8919,
          "probability": 0.7318,
          "probability_lcb": 0.501,
          "reasons": [
            "forecast source spread 8.1F exceeds max 7.0F; point blend is unreliable",
            "NO bid size 0.70 below min 1.00",
            "model/market gap 0.246 exceeds max 0.150",
            "lower-bound edge -0.159 below min 0.000"
          ],
          "recommended_contracts": 0.0,
          "recommended_spend": 0.0,
          "remaining_heat_risk": 0.904,
          "residual_probability": 0.8747,
          "side": "NO",
          "spread": 0.01,
          "ticker": "KXHIGHTSFO-26JUN25-B69.5",
          "trade_quality_score": 34.7
        },
        {
          "action": "BUY_NO",
          "approved": false,
          "ask": 0.98,
          "bid": 0.97,
          "decision": "NO_TRADE",
          "edge": -0.0504,
          "edge_lcb": -0.1108,
          "ensemble_probability": 1.0,
          "expected_profit": -0.0,
          "intraday_probability": 0.8491,
          "label": "63\u00b0 to 64\u00b0",
          "market_probability": 0.9757,
          "model_probability": 0.8725,
          "probability": 0.9396,
          "probability_lcb": 0.8792,
          "reasons": [
            "forecast source spread 8.1F exceeds max 7.0F; point blend is unreliable",
            "edge -0.050 below min 0.020",
            "lower-bound edge -0.111 below min 0.000"
          ],
          "recommended_contracts": 0.0,
          "recommended_spend": 0.0,
          "remaining_heat_risk": 0.904,
          "residual_probability": 0.829,
          "side": "NO",
          "spread": 0.01,
          "ticker": "KXHIGHTSFO-26JUN25-B63.5",
          "trade_quality_score": 29.8
        },
        {
          "action": "BUY_YES",
          "approved": false,
          "ask": 0.06,
          "bid": 0.05,
          "decision": "NO_TRADE",
          "edge": 0.0483,
          "edge_lcb": -0.07,
          "ensemble_probability": 0.3226,
          "expected_profit": 0.0,
          "intraday_probability": 0.2264,
          "label": "65\u00b0 to 66\u00b0",
          "market_probability": 0.0534,
          "model_probability": 0.2387,
          "probability": 0.1183,
          "probability_lcb": 0.0,
          "reasons": [
            "forecast source spread 8.1F exceeds max 7.0F; point blend is unreliable",
            "model/market gap 0.185 exceeds max 0.150",
            "lower-bound edge -0.070 below min 0.000",
            "1c/2c tail requires exceptional support (YES): bid size 1.00<10.00, p_lcb 0.000<0.090, edge_lcb -0.070<0.030, model/market gap 0.185>0.080",
            "YES lower-bound edge -0.070 is not positive",
            "cheap YES (cost 0.07) needs point probability >= 2x cost (0.14); have 0.12"
          ],
          "recommended_contracts": 0.0,
          "recommended_spend": 0.0,
          "remaining_heat_risk": 0.904,
          "residual_probability": 0.2087,
          "side": "YES",
          "spread": 0.01,
          "ticker": "KXHIGHTSFO-26JUN25-B65.5",
          "trade_quality_score": 29.5
        },
        {
          "action": "BUY_YES",
          "approved": false,
          "ask": 0.36,
          "bid": 0.35,
          "decision": "NO_TRADE",
          "edge": -0.1126,
          "edge_lcb": -0.345,
          "ensemble_probability": 0.0,
          "expected_profit": -0.0,
          "intraday_probability": 0.122,
          "label": "71\u00b0 or above",
          "market_probability": 0.3447,
          "model_probability": 0.1239,
          "probability": 0.2674,
          "probability_lcb": 0.035,
          "reasons": [
            "forecast source spread 8.1F exceeds max 7.0F; point blend is unreliable",
            "model/market gap 0.221 exceeds max 0.150",
            "edge -0.113 below min 0.020",
            "lower-bound edge -0.345 below min 0.000",
            "YES lower-bound edge -0.345 is not positive"
          ],
          "recommended_contracts": 0.0,
          "recommended_spend": 0.0,
          "remaining_heat_risk": 0.904,
          "residual_probability": 0.1778,
          "side": "YES",
          "spread": 0.01,
          "ticker": "KXHIGHTSFO-26JUN25-T70",
          "trade_quality_score": 25.6
        },
        {
          "action": "BUY_YES",
          "approved": false,
          "ask": 0.25,
          "bid": 0.2,
          "decision": "NO_TRADE",
          "edge": -0.0053,
          "edge_lcb": -0.2547,
          "ensemble_probability": 0.6774,
          "expected_profit": -0.0,
          "intraday_probability": 0.2353,
          "label": "67\u00b0 to 68\u00b0",
          "market_probability": 0.2184,
          "model_probability": 0.3037,
          "probability": 0.2647,
          "probability_lcb": 0.0153,
          "reasons": [
            "forecast source spread 8.1F exceeds max 7.0F; point blend is unreliable",
            "edge -0.005 below min 0.020",
            "lower-bound edge -0.255 below min 0.000",
            "YES lower-bound edge -0.255 is not positive"
          ],
          "recommended_contracts": 0.0,
          "recommended_spend": 0.0,
          "remaining_heat_risk": 0.904,
          "residual_probability": 0.1761,
          "side": "YES",
          "spread": 0.05,
          "ticker": "KXHIGHTSFO-26JUN25-B67.5",
          "trade_quality_score": 23.3
        },
        {
          "action": "BUY_YES",
          "approved": false,
          "ask": 0.01,
          "bid": 0.0,
          "decision": "NO_TRADE",
          "edge": 0.0175,
          "edge_lcb": -0.02,
          "ensemble_probability": 0.0,
          "expected_profit": 0.0,
          "intraday_probability": 0.096,
          "label": "62\u00b0 or below",
          "market_probability": 0.0049,
          "model_probability": 0.0981,
          "probability": 0.0375,
          "probability_lcb": 0.0,
          "reasons": [
            "forecast source spread 8.1F exceeds max 7.0F; point blend is unreliable",
            "YES bid 0.00 below min 0.01; no exit support",
            "YES bid size 0.00 below min 1.00",
            "spread 0.01 is 100% of YES ask 0.01; exit would start beyond the 35% stop band",
            "posterior probability 0.038 below min 0.070",
            "edge 0.018 below min 0.020",
            "lower-bound edge -0.020 below min 0.000",
            "1c/2c tail requires exceptional support (YES): bid 0.00<0.01, bid size 0.00<10.00, p_lcb 0.000<0.090, edge_lcb -0.020<0.030, model/market gap 0.093>0.080, ensemble p 0.000<0.080",
            "YES lower-bound edge -0.020 is not positive",
            "cheap YES (cost 0.02) needs point probability >= 2x cost (0.04); have 0.04"
          ],
          "recommended_contracts": 0.0,
          "recommended_spend": 0.0,
          "remaining_heat_risk": 0.904,
          "residual_probability": 0.1412,
          "side": "YES",
          "spread": 0.01,
          "ticker": "KXHIGHTSFO-26JUN25-T63",
          "trade_quality_score": 20.4
        }
      ],
      "ensemble": {
        "cell_selection": "nearest",
        "member_count": 31,
        "source": "open_meteo_gfs_ensemble",
        "station_bias_f": 5.08,
        "station_mean_high_f": 66.71,
        "station_std_high_f": 0.57,
        "warning": "raw grid mean shifted by +5.1F to match SFO station center; nearby Open-Meteo grid means differ by 10.4F (nearest=61.6F, land=72.0F); using nearest"
      },
      "event_title": "Highest temperature in San Francisco on Jun 25, 2026?",
      "forecast": {
        "calls_used_today": 30,
        "fetched_at": "2026-06-25T12:10:20.571336+00:00",
        "fresh_station_count": 4,
        "lead_hours": 8.83,
        "max_calls_per_day": 260,
        "method": "weighted blend floored by NWS observed high-so-far",
        "predicted_high_f": 66.71,
        "source_count": 4,
        "source_spread_f": 8.1,
        "sources": {
          "google_high_f": 62.7,
          "history_high_f": 70.8,
          "nws_high_f": 68.0,
          "open_meteo_high_f": 67.7
        },
        "target_date": "2026-06-25"
      },
      "intraday": {
        "forecast_fetched_at": "2026-06-25T12:10:20.571336+00:00",
        "is_complete": false,
        "latest_observed_at": "2026-06-25T08:00:00+00:00",
        "latest_temp_f": 57.2,
        "observation_count": 52,
        "observed_high_f": 57.2,
        "observed_high_source": "NWS station observations",
        "remaining_forecast_high_f": 62.7,
        "target_date": "2026-06-25"
      },
      "market_available": true,
      "market_consensus": {
        "available": true,
        "distribution": [
          {
            "center_f": 61.5,
            "implied_probability": 0.0092,
            "label": "62\u00b0 or below",
            "model_probability": 0.0981,
            "ticker": "KXHIGHTSFO-26JUN25-T63"
          },
          {
            "center_f": 63.5,
            "implied_probability": 0.0183,
            "label": "63\u00b0 to 64\u00b0",
            "model_probability": 0.1275,
            "ticker": "KXHIGHTSFO-26JUN25-B63.5"
          },
          {
            "center_f": 65.5,
            "implied_probability": 0.055,
            "label": "65\u00b0 to 66\u00b0",
            "model_probability": 0.2387,
            "ticker": "KXHIGHTSFO-26JUN25-B65.5"
          },
          {
            "center_f": 67.5,
            "implied_probability": 0.2477,
            "label": "67\u00b0 to 68\u00b0",
            "model_probability": 0.3037,
            "ticker": "KXHIGHTSFO-26JUN25-B67.5"
          },
          {
            "center_f": 69.5,
            "implied_probability": 0.3394,
            "label": "69\u00b0 to 70\u00b0",
            "model_probability": 0.1081,
            "ticker": "KXHIGHTSFO-26JUN25-B69.5"
          },
          {
            "center_f": 71.5,
            "implied_probability": 0.3303,
            "label": "71\u00b0 or above",
            "model_probability": 0.1239,
            "ticker": "KXHIGHTSFO-26JUN25-T70"
          }
        ],
        "implied_high_f": 69.26,
        "implied_stdev_f": 2.0937,
        "liquid_bin_count": 5,
        "median_f": 69.5,
        "modal_bin_label": "69\u00b0 to 70\u00b0",
        "modal_bin_ticker": "KXHIGHTSFO-26JUN25-B69.5",
        "modal_probability": 0.3394,
        "model_high_f": 66.71,
        "model_minus_market_f": -2.55,
        "overround": 0.09,
        "p10_f": 66.6407,
        "p25_f": 67.8519,
        "p75_f": 70.9861,
        "p90_f": 71.8944
      },
      "target_date": "2026-06-25",
      "warnings": []
    },
    {
      "best_decision": {
        "action": "BUY_YES",
        "approved": false,
        "ask": 0.0,
        "bid": 0.0,
        "decision": "NO_TRADE",
        "edge": 0.341,
        "edge_lcb": 0.135,
        "ensemble_probability": 0.6774,
        "expected_profit": 0.0,
        "intraday_probability": null,
        "label": "66\u00b0 to 67\u00b0",
        "market_probability": null,
        "model_probability": 0.341,
        "probability": 0.341,
        "probability_lcb": 0.135,
        "reasons": [
          "market status is initialized, not active",
          "YES ask is not tradeable"
        ],
        "recommended_contracts": 0.0,
        "recommended_spend": 0.0,
        "remaining_heat_risk": null,
        "residual_probability": 0.1969,
        "side": "YES",
        "spread": 0.0,
        "ticker": "KXHIGHTSFO-26JUN26-B66.5",
        "trade_quality_score": 64.2
      },
      "decisions": [
        {
          "action": "BUY_YES",
          "approved": false,
          "ask": 0.0,
          "bid": 0.0,
          "decision": "NO_TRADE",
          "edge": 0.341,
          "edge_lcb": 0.135,
          "ensemble_probability": 0.6774,
          "expected_profit": 0.0,
          "intraday_probability": null,
          "label": "66\u00b0 to 67\u00b0",
          "market_probability": null,
          "model_probability": 0.341,
          "probability": 0.341,
          "probability_lcb": 0.135,
          "reasons": [
            "market status is initialized, not active",
            "YES ask is not tradeable"
          ],
          "recommended_contracts": 0.0,
          "recommended_spend": 0.0,
          "remaining_heat_risk": null,
          "residual_probability": 0.1969,
          "side": "YES",
          "spread": 0.0,
          "ticker": "KXHIGHTSFO-26JUN26-B66.5",
          "trade_quality_score": 64.2
        },
        {
          "action": "BUY_YES",
          "approved": false,
          "ask": 0.0,
          "bid": 0.0,
          "decision": "NO_TRADE",
          "edge": 0.1911,
          "edge_lcb": 0.0876,
          "ensemble_probability": 0.1613,
          "expected_profit": 0.0,
          "intraday_probability": null,
          "label": "64\u00b0 to 65\u00b0",
          "market_probability": null,
          "model_probability": 0.1911,
          "probability": 0.1911,
          "probability_lcb": 0.0876,
          "reasons": [
            "market status is initialized, not active",
            "YES ask is not tradeable"
          ],
          "recommended_contracts": 0.0,
          "recommended_spend": 0.0,
          "remaining_heat_risk": null,
          "residual_probability": 0.2038,
          "side": "YES",
          "spread": 0.0,
          "ticker": "KXHIGHTSFO-26JUN26-B64.5",
          "trade_quality_score": 63.1
        },
        {
          "action": "BUY_YES",
          "approved": false,
          "ask": 0.0,
          "bid": 0.0,
          "decision": "NO_TRADE",
          "edge": 0.1509,
          "edge_lcb": 0.0594,
          "ensemble_probability": 0.1613,
          "expected_profit": 0.0,
          "intraday_probability": null,
          "label": "68\u00b0 to 69\u00b0",
          "market_probability": null,
          "model_probability": 0.1509,
          "probability": 0.1509,
          "probability_lcb": 0.0594,
          "reasons": [
            "market status is initialized, not active",
            "YES ask is not tradeable"
          ],
          "recommended_contracts": 0.0,
          "recommended_spend": 0.0,
          "remaining_heat_risk": null,
          "residual_probability": 0.1464,
          "side": "YES",
          "spread": 0.0,
          "ticker": "KXHIGHTSFO-26JUN26-B68.5",
          "trade_quality_score": 56.9
        },
        {
          "action": "BUY_YES",
          "approved": false,
          "ask": 0.0,
          "bid": 0.0,
          "decision": "NO_TRADE",
          "edge": 0.1593,
          "edge_lcb": 0.0238,
          "ensemble_probability": 0.0,
          "expected_profit": 0.0,
          "intraday_probability": null,
          "label": "63\u00b0 or below",
          "market_probability": null,
          "model_probability": 0.1593,
          "probability": 0.1593,
          "probability_lcb": 0.0238,
          "reasons": [
            "market status is initialized, not active",
            "YES ask is not tradeable"
          ],
          "recommended_contracts": 0.0,
          "recommended_spend": 0.0,
          "remaining_heat_risk": null,
          "residual_probability": 0.2276,
          "side": "YES",
          "spread": 0.0,
          "ticker": "KXHIGHTSFO-26JUN26-T64",
          "trade_quality_score": 47.0
        },
        {
          "action": "BUY_NO",
          "approved": false,
          "ask": 1.0,
          "bid": 1.0,
          "decision": "NO_TRADE",
          "edge": -0.1509,
          "edge_lcb": -0.2423,
          "ensemble_probability": 0.8387,
          "expected_profit": -0.0,
          "intraday_probability": null,
          "label": "68\u00b0 to 69\u00b0",
          "market_probability": null,
          "model_probability": 0.8491,
          "probability": 0.8491,
          "probability_lcb": 0.7577,
          "reasons": [
            "market status is initialized, not active",
            "NO ask is not tradeable",
            "all-in cost 1.00 meets or exceeds the $1 contract payout",
            "edge -0.151 below min 0.020",
            "lower-bound edge -0.242 below min 0.000"
          ],
          "recommended_contracts": 0.0,
          "recommended_spend": 0.0,
          "remaining_heat_risk": null,
          "residual_probability": 0.8536,
          "side": "NO",
          "spread": 0.0,
          "ticker": "KXHIGHTSFO-26JUN26-B68.5",
          "trade_quality_score": 39.0
        },
        {
          "action": "BUY_NO",
          "approved": false,
          "ask": 1.0,
          "bid": 1.0,
          "decision": "NO_TRADE",
          "edge": -0.1911,
          "edge_lcb": -0.2946,
          "ensemble_probability": 0.8387,
          "expected_profit": -0.0,
          "intraday_probability": null,
          "label": "64\u00b0 to 65\u00b0",
          "market_probability": null,
          "model_probability": 0.8089,
          "probability": 0.8089,
          "probability_lcb": 0.7054,
          "reasons": [
            "market status is initialized, not active",
            "NO ask is not tradeable",
            "all-in cost 1.00 meets or exceeds the $1 contract payout",
            "edge -0.191 below min 0.020",
            "lower-bound edge -0.295 below min 0.000"
          ],
          "recommended_contracts": 0.0,
          "recommended_spend": 0.0,
          "remaining_heat_risk": null,
          "residual_probability": 0.7962,
          "side": "NO",
          "spread": 0.0,
          "ticker": "KXHIGHTSFO-26JUN26-B64.5",
          "trade_quality_score": 38.2
        },
        {
          "action": "BUY_NO",
          "approved": false,
          "ask": 1.0,
          "bid": 1.0,
          "decision": "NO_TRADE",
          "edge": -0.0677,
          "edge_lcb": -0.1355,
          "ensemble_probability": 1.0,
          "expected_profit": -0.0,
          "intraday_probability": null,
          "label": "70\u00b0 to 71\u00b0",
          "market_probability": null,
          "model_probability": 0.9323,
          "probability": 0.9323,
          "probability_lcb": 0.8645,
          "reasons": [
            "market status is initialized, not active",
            "NO ask is not tradeable",
            "all-in cost 1.00 meets or exceeds the $1 contract payout",
            "edge -0.068 below min 0.020",
            "lower-bound edge -0.135 below min 0.000"
          ],
          "recommended_contracts": 0.0,
          "recommended_spend": 0.0,
          "remaining_heat_risk": null,
          "residual_probability": 0.9032,
          "side": "NO",
          "spread": 0.0,
          "ticker": "KXHIGHTSFO-26JUN26-B70.5",
          "trade_quality_score": 36.7
        },
        {
          "action": "BUY_YES",
          "approved": false,
          "ask": 0.0,
          "bid": 0.0,
          "decision": "NO_TRADE",
          "edge": 0.09,
          "edge_lcb": 0.0,
          "ensemble_probability": 0.0,
          "expected_profit": 0.0,
          "intraday_probability": null,
          "label": "72\u00b0 or above",
          "market_probability": null,
          "model_probability": 0.09,
          "probability": 0.09,
          "probability_lcb": 0.0,
          "reasons": [
            "market status is initialized, not active",
            "YES ask is not tradeable",
            "YES lower-bound edge 0.000 is not positive"
          ],
          "recommended_contracts": 0.0,
          "recommended_spend": 0.0,
          "remaining_heat_risk": null,
          "residual_probability": 0.1285,
          "side": "YES",
          "spread": 0.0,
          "ticker": "KXHIGHTSFO-26JUN26-T71",
          "trade_quality_score": 36.1
        },
        {
          "action": "BUY_NO",
          "approved": false,
          "ask": 1.0,
          "bid": 1.0,
          "decision": "NO_TRADE",
          "edge": -0.09,
          "edge_lcb": -0.18,
          "ensemble_probability": 1.0,
          "expected_profit": -0.0,
          "intraday_probability": null,
          "label": "72\u00b0 or above",
          "market_probability": null,
          "model_probability": 0.91,
          "probability": 0.91,
          "probability_lcb": 0.82,
          "reasons": [
            "market status is initialized, not active",
            "NO ask is not tradeable",
            "all-in cost 1.00 meets or exceeds the $1 contract payout",
            "edge -0.090 below min 0.020",
            "lower-bound edge -0.180 below min 0.000"
          ],
          "recommended_contracts": 0.0,
          "recommended_spend": 0.0,
          "remaining_heat_risk": null,
          "residual_probability": 0.8715,
          "side": "NO",
          "spread": 0.0,
          "ticker": "KXHIGHTSFO-26JUN26-T71",
          "trade_quality_score": 35.8
        },
        {
          "action": "BUY_YES",
          "approved": false,
          "ask": 0.0,
          "bid": 0.0,
          "decision": "NO_TRADE",
          "edge": 0.0677,
          "edge_lcb": 0.0,
          "ensemble_probability": 0.0,
          "expected_profit": 0.0,
          "intraday_probability": null,
          "label": "70\u00b0 to 71\u00b0",
          "market_probability": null,
          "model_probability": 0.0677,
          "probability": 0.0677,
          "probability_lcb": 0.0,
          "reasons": [
            "market status is initialized, not active",
            "YES ask is not tradeable",
            "posterior probability 0.068 below min 0.070",
            "YES lower-bound edge 0.000 is not positive"
          ],
          "recommended_contracts": 0.0,
          "recommended_spend": 0.0,
          "remaining_heat_risk": null,
          "residual_probability": 0.0968,
          "side": "YES",
          "spread": 0.0,
          "ticker": "KXHIGHTSFO-26JUN26-B70.5",
          "trade_quality_score": 33.7
        },
        {
          "action": "BUY_NO",
          "approved": false,
          "ask": 1.0,
          "bid": 1.0,
          "decision": "NO_TRADE",
          "edge": -0.1593,
          "edge_lcb": -0.2948,
          "ensemble_probability": 1.0,
          "expected_profit": -0.0,
          "intraday_probability": null,
          "label": "63\u00b0 or below",
          "market_probability": null,
          "model_probability": 0.8407,
          "probability": 0.8407,
          "probability_lcb": 0.7052,
          "reasons": [
            "market status is initialized, not active",
            "NO ask is not tradeable",
            "all-in cost 1.00 meets or exceeds the $1 contract payout",
            "edge -0.159 below min 0.020",
            "lower-bound edge -0.295 below min 0.000"
          ],
          "recommended_contracts": 0.0,
          "recommended_spend": 0.0,
          "remaining_heat_risk": null,
          "residual_probability": 0.7724,
          "side": "NO",
          "spread": 0.0,
          "ticker": "KXHIGHTSFO-26JUN26-T64",
          "trade_quality_score": 33.0
        },
        {
          "action": "BUY_NO",
          "approved": false,
          "ask": 1.0,
          "bid": 1.0,
          "decision": "NO_TRADE",
          "edge": -0.341,
          "edge_lcb": -0.547,
          "ensemble_probability": 0.3226,
          "expected_profit": -0.0,
          "intraday_probability": null,
          "label": "66\u00b0 to 67\u00b0",
          "market_probability": null,
          "model_probability": 0.659,
          "probability": 0.659,
          "probability_lcb": 0.453,
          "reasons": [
            "market status is initialized, not active",
            "NO ask is not tradeable",
            "all-in cost 1.00 meets or exceeds the $1 contract payout",
            "edge -0.341 below min 0.020",
            "lower-bound edge -0.547 below min 0.000"
          ],
          "recommended_contracts": 0.0,
          "recommended_spend": 0.0,
          "remaining_heat_risk": null,
          "residual_probability": 0.8031,
          "side": "NO",
          "spread": 0.0,
          "ticker": "KXHIGHTSFO-26JUN26-B66.5",
          "trade_quality_score": 32.4
        }
      ],
      "ensemble": {
        "cell_selection": "land",
        "member_count": 31,
        "source": "open_meteo_gfs_ensemble",
        "station_bias_f": -1.06,
        "station_mean_high_f": 66.61,
        "station_std_high_f": 0.96,
        "warning": null
      },
      "event_title": "Highest temperature in San Francisco on Jun 26, 2026?",
      "forecast": {
        "calls_used_today": 30,
        "fetched_at": "2026-06-25T12:10:20.571336+00:00",
        "fresh_station_count": 4,
        "lead_hours": 32.83,
        "max_calls_per_day": 260,
        "method": "weighted Google + NWS + Open-Meteo + SFO history with capped station adjustment",
        "predicted_high_f": 66.61,
        "source_count": 4,
        "source_spread_f": 6.0,
        "sources": {
          "google_high_f": 64.8,
          "history_high_f": 70.7,
          "nws_high_f": 68.0,
          "open_meteo_high_f": 64.7
        },
        "target_date": "2026-06-26"
      },
      "intraday": null,
      "market_available": true,
      "market_consensus": {
        "available": false
      },
      "target_date": "2026-06-26",
      "warnings": []
    }
  ]
}
